Workbook

Sheet Detalle de Costos
D3: Costos por paquete de trabajo
A6: Planificació de estartegias de identificación y retención de clientes para generación de marketing
A7: LTV_str | B7: Paquete de Trabajo
A8: Semanas | C8: 1 | D8: 2 | E8: 3 | F8: 4 | G8: 5 | H8: 6 | I8: 7 | J8: 8 | K8: 9 | L8: 10 | M8: 11 | N8: 12 | O8: 13 | P8: 14 | Q8: 15 | R8: 16 | S8: 17 | T8: 18 | U8: 19 | V8: 20 | W8: 21 | X8: 22 | Y8: 23 | Z8: 24 | AA8: 25 | AB8: 26 | AC8: 27 | AD8: 28 | AE8: 29 | AF8: 30 | AG8: 31 | AH8: 32 | AI8: 33 | AJ8: 34 | AK8: 35 | AL8: 36 | AM8: 37 | AN8: 38 | AO8: 39 | AP8: 40 | AQ8: 41 | AR8: 42 | AS8: 43 | AT8: 44 | AU8: 45 | AV8: 46 | AW8: 47 | AX8: 48 | AY8: 49 | AZ8: 50 | BA8: 51 | BB8: 52 | BC8: 53 | BD8: 54 | BE8: 55 | BF8: 56 | BG8: 57 | BH8: 58 | BI8: 59 | BJ8: 60
A9: Inicio y comprensión del proyecto
A10: 1.1 | B10: Definición del problema de negocio y objetivos del CLV | C10: 10000
A11: 1.2 | B11: Identificación de KPIs y decisiones de negocio | C11: 7500
A12: 1.3 | B12: Descarga y revisión del Dataset Online Retail | C12: 6000
A13: 1.4 | B13: Análisis exploratorio inicial del dataset (EDA) | D13: 12000
A14: 1.5 | B14: Identificación de valores nulo y datos inválidos | D14: 6000
A15: 1.6 | B15: Limpieza de transacciones (devoluciones, precios negativos) | E15: 6000
A16: 1.7 | B16: Creación de variable Revenue | E16: 2500
A17: 1.8 | B17: Validacion final del dataset limpio | F17: 2500
A18: Análisis RFM
A19: 2.1 | B19: Definición de fecha de referencia para RFM | G19: 5000
A20: 2.2 | B20: Cálculo de métricas Recency, Frequency y Monetary | G20: 15000
A21: 2.3 | B21: Normalización y análisis estadístico RFM | H21: 12000
A22: 2.4 | B22: Segmentación de clientes RFM | H22: 10000
A23: Feature Engineering y preparación para CLV
A24: 3.1 | B24: Definición de ventana temporal de observación y predicción | I24: 8000
A25: 3.2 | B25: Creación de variables adicionales | I25: 18000
A26: 3.3 | B26: Preparación del dataset para modelos CLV | J26: 14500
A27: 3.4 | B27: Separación de datos (train/validación) | J27: 12000
A28: Modelado del Customer Lifetime Value
A29: 4.1 | B29: Implementación del modelo BG/NBD | J29: 20000
A30: 4.2 | B30: Implementación del modelo Gamma-Gamma | J30: 18000
A31: 4.3 | B31: Entrenamiento y ajuste de modelos CLV | K31: 22500
A32: 4.4 | B32: Evaluación y validación del modelo CLV | K32: 20000
A33: Segmentación basada en CLV
A34: 5.1 | B34: Predicción de CLV por cliente | K34: 10000
A35: 5.2 | B35: Segmentación de clientes por niveles de CLV | K35: 9000
A36: 5.3 | B36: Cruce de segmentación CLV + RFM | L36: 7000
A37: 5.4 | B37: Identificaci+ón swl 20% de clientes de mayor valor | L37: 9000
A38: Estrategias de marketing y ROI
A39: 6.1 | B39: Definición de estrategias por segmento de clientes | M39: 18000
A40: 6.2 | B40: Asignación de presupuesto de marketing por segmento | M40: 15000
A41: 6.3 | B41: Simulación de impacto y ROI de las estrategias | M41: 20000
A42: 6.4 | B42: Elaboración de visualizaciones y dashboards finales | N42: 14500
A43: 6.5 | B43: Preparación del reporte y presentación ejecutiva | N43: 12000
A44: 6.6 | B44: Documentación técnica y cierre del proyecto | N44: 8000
B45: TOTAL | C45: =SUM(C10:C44) -> 23500 | D45: =SUM(D10:D44) -> 18000 | E45: =SUM(E10:E44) -> 8500 | F45: =SUM(F10:F44) -> 2500 | G45: =SUM(G10:G44) -> 20000 | H45: =SUM(H10:H44) -> 22000 | I45: =SUM(I10:I44) -> 26000 | J45: =SUM(J10:J44) -> 64500 | ... BJ45: =SUM(BJ10:BJ44) -> 0
C47: Costos por fases
B48: =SUM(C48:H48) -> 350000 | C48: =SUM(C10:C12,D13:D14,E15:E16,F18,F17) -> 52500 | D48: =SUM(G19:G20,H21:H22) -> 42000 | E48: =SUM(I24:I25,J26:J27) -> 52500 | F48: =SUM(J29:J30,K31:K32) -> 80500 | G48: =SUM(K34:K35,L36:L37) -> 35000 | H48: =SUM(M39:M41,N42:N44) -> 87500
C49: 1 | D49: 2 | E49: 3 | F49: 4 | G49: 5 | H49: 6

Sheet Plantilla Curva S
C7: Curva S de Recursos
C9: Proyecto: | D9: Planificació de estartegias de identificación y retención de clientes para generación de marketing
C10: ID: | D10: LTV_str
C11: Fecha de Inicio | D11: 16 de febrero de 2026 | F11: Fecha Fin: | H11: 27 de febrero de 2026 | K11: Fecha de Corte: | M11: 25 de febrero de 2026
D13: Semanas
D14: 1 | E14: 2 | F14: 3 | G14: 4 | H14: 5 | I14: 6 | J14: 7 | K14: 8 | L14: 9 | M14: 10 | N14: 11 | O14: 12
C15: Valor Planificado | D15: ='Detalle de Costos'!C45 -> 23500 | E15: ='Detalle de Costos'!D45 -> 18000 | F15: ='Detalle de Costos'!E45 -> 8500 | G15: ='Detalle de Costos'!F45 -> 2500 | H15: ='Detalle de Costos'!G45 -> 20000 | I15: ='Detalle de Costos'!H45 -> 22000 | J15: ='Detalle de Costos'!I45 -> 26000 | K15: ='Detalle de Costos'!J45 -> 64500 | ... O15: ='Detalle de Costos'!N45 -> 34500
C16: Valor Planificado Acumulado | D16: =D15 -> 23500 | E16: =E15+D16 -> 41500 | F16: =F15+E16 -> 50000 | G16: =G15+F16 -> 52500 | H16: =H15+G16 -> 72500 | I16: =I15+H16 -> 94500 | J16: =J15+I16 -> 120500 | K16: =K15+J16 -> 185000 | L16: =L15+K16 -> 246500 | ... O16: =O15+N16 -> 350000
C17: Costo Real | D17: 23000 | E17: 16000
C18: Costo Real Acumulado | D18: 23000 | E18: =D18+E17 -> 39000
